summarizeGPT/__init__.py
summarizeGPT/summarizeGPT.py
tests/__init__.py
tests/test_summarize_gpt.py
SummarizeGPT-1.4.dist-info/LICENSE
SummarizeGPT-1.4.dist-info/METADATA
SummarizeGPT-1.4.dist-info/WHEEL
SummarizeGPT-1.4.dist-info/entry_points.txt
SummarizeGPT-1.4.dist-info/top_level.txt
SummarizeGPT-1.4.dist-info/RECORD
