Metadata-Version: 2.2
Name: SummarizeGPT
Version: 1.4
Summary: Tool to summarize directories of code for prompting with LLMs
Home-page: https://github.com/Maralai/SummarizeGPT
Author: Matt Harrison
Author-email: matt@harrison.consulting
License: GPL-3.0
Classifier: Programming Language :: Python :: 3
Classifier: Programming Language :: Python :: 3.6
Classifier: Programming Language :: Python :: 3.7
Classifier: Programming Language :: Python :: 3.8
Classifier: Programming Language :: Python :: 3.9
Classifier: License :: OSI Approved :: GNU General Public License v3 (GPLv3)
License-File: LICENSE
Requires-Dist: gitignore_parser
Requires-Dist: tiktoken
Dynamic: author
Dynamic: author-email
Dynamic: classifier
Dynamic: description
Dynamic: description-content-type
Dynamic: home-page
Dynamic: license
Dynamic: requires-dist
Dynamic: summary
